smadi/__init__.py
smadi/anomaly_detectors.py
smadi/climatology.py
smadi/data_reader.py
smadi/indicators.py
smadi/map.py
smadi/metadata.py
smadi/plot.py
smadi/preprocess.py
smadi/utils.py
smadi/workflow.py
smadi-1.1.1.dist-info/LICENSE.txt
smadi-1.1.1.dist-info/METADATA
smadi-1.1.1.dist-info/WHEEL
smadi-1.1.1.dist-info/entry_points.txt
smadi-1.1.1.dist-info/top_level.txt
smadi-1.1.1.dist-info/RECORD
