Metadata-Version: 2.1
Name: smadi
Version: 1.1.1
Summary: Add a short description here!
Home-page: https://github.com/MuhammedM294/smadi
Author: MuhammedM294
Author-email: muhammedaabdelaal@gmail.com
License: MIT
Project-URL: Documentation, https://pyscaffold.org/
Project-URL: Source, https://github.com/MuhammedM294/smadi
Platform: any
Classifier: Development Status :: 4 - Beta
Classifier: Programming Language :: Python
Requires-Python: >=3.8
License-File: LICENSE.txt
Requires-Dist: setuptools
Requires-Dist: pyscaffold
Requires-Dist: autopep8
Requires-Dist: numpy
Requires-Dist: scipy
Requires-Dist: pandas
Requires-Dist: netCDF4
Requires-Dist: matplotlib
Requires-Dist: numba
Requires-Dist: eomaps
Requires-Dist: statsmodels
Requires-Dist: scikit-learn
Requires-Dist: cartopy
Requires-Dist: xarray
Requires-Dist: dask
Requires-Dist: flake8
Requires-Dist: pyflakes
Requires-Dist: yapf
Requires-Dist: cadati
Requires-Dist: pytesmo
Requires-Dist: ascat
Requires-Dist: pygeobase
Requires-Dist: pygeogrids
Requires-Dist: pynetcf
Requires-Dist: cmcrameri
Requires-Dist: fibgrid
Requires-Dist: datashader
Requires-Dist: pycountry
Requires-Dist: PyQt5
Requires-Dist: PySide2
Requires-Dist: mapclassify
Requires-Dist: standard-precip
Requires-Dist: tqdm
Requires-Dist: importlib-metadata ; python_version < "3.8"
Provides-Extra: testing
Requires-Dist: setuptools ; extra == 'testing'
Requires-Dist: pytest ; extra == 'testing'
Requires-Dist: pytest-cov ; extra == 'testing'
